{"users": [{"id": 15966, "slack_id": "U096DRNAPGV", "display_name": "johan elango", "bio": null, "projects_count": 0, "devlogs_count": 0, "votes_count": 0, "ships_count": 0, "projects": [], "coding_time_seconds": 0, "coding_time_seconds_today": 0, "balance": "You need to have a pocket watcher badge to view this.", "badges": [], "created_at": "2025-07-18T10:03:09.540-04:00", "updated_at": "2025-07-18T21:24:50.427-04:00", "avatar": "https://avatars.slack-edge.com/2025-07-18/9242709303584_d69b1875166ea30a9f95_original.jpg", "custom_css": null}, {"id": 15967, "slack_id": "U08241XPC6P", "display_name": "Quelqu_n", "bio": null, "projects_count": 0, "devlogs_count": 0, "votes_count": 1, "ships_count": 0, "projects": [], "coding_time_seconds": 0, "coding_time_seconds_today": 0, "balance": "You need to have a pocket watcher badge to view this.", "badges": [], "created_at": "2025-07-18T10:05:20.037-04:00", "updated_at": "2025-07-18T13:22:37.443-04:00", "avatar": "https://avatars.slack-edge.com/2024-11-30/8108220927636_b90cbc172961469e6dcf_original.jpg", "custom_css": null}, {"id": 15968, "slack_id": "U096VFWKRJM", "display_name": "MUHSIN M P", "bio": null, "projects_count": 0, "devlogs_count": 0, "votes_count": 0, "ships_count": 0, "projects": [], "coding_time_seconds": 0, "coding_time_seconds_today": 0, "balance": "You need to have a pocket watcher badge to view this.", "badges": [], "created_at": "2025-07-18T10:13:46.293-04:00", "updated_at": "2025-07-18T21:24:54.605-04:00", "avatar": "https://secure.gravatar.com/avatar/13a67e9cf8b24c04cf9a3af55eb10df6.jpg?s=512&d=https%3A%2F%2Fa.slack-edge.com%2Fdf10d%2Fimg%2Favatars%2Fava_0008-512.png", "custom_css": null}, {"id": 15969, "slack_id": "U096DTJMUN9", "display_name": "Ramzan Khan", "bio": null, "projects_count": 0, "devlogs_count": 0, "votes_count": 0, "ships_count": 0, "projects": [], "coding_time_seconds": 0, "coding_time_seconds_today": 0, "balance": "You need to have a pocket watcher badge to view this.", "badges": [], "created_at": "2025-07-18T10:14:53.615-04:00", "updated_at": "2025-08-19T03:24:48.427-04:00", "avatar": "https://avatars.slack-edge.com/2025-08-19/9372477807810_da6a2b43ad6803167b11_original.jpg", "custom_css": null}, {"id": 15970, "slack_id": "U096H3J6H1S", "display_name": "aja p", "bio": null, "projects_count": 0, "devlogs_count": 0, "votes_count": 0, "ships_count": 0, "projects": [], "coding_time_seconds": 0, "coding_time_seconds_today": 0, "balance": "You need to have a pocket watcher badge to view this.", "badges": [], "created_at": "2025-07-18T10:27:20.423-04:00", "updated_at": "2025-07-22T10:04:40.780-04:00", "avatar": "https://avatars.slack-edge.com/2025-07-18/9217924388405_daf36154d768a8e3bd46_original.jpg", "custom_css": null}, {"id": 15971, "slack_id": "U096CLENGLW", "display_name": "MOHIT KUMAR", "bio": null, "projects_count": 0, "devlogs_count": 0, "votes_count": 0, "ships_count": 0, "projects": [], "coding_time_seconds": 89025, "coding_time_seconds_today": 1390, "balance": "You need to have a pocket watcher badge to view this.", "badges": [], "created_at": "2025-07-18T10:37:02.685-04:00", "updated_at": "2025-07-18T21:24:54.826-04:00", "avatar": "https://avatars.slack-edge.com/2025-07-18/9214839004627_1f0157b26281c1fcda53_original.png", "custom_css": null}, {"id": 15972, "slack_id": "U096B669PMH", "display_name": "dumdog", "bio": "I have ADHD, so everything has go fast", "projects_count": 0, "devlogs_count": 18, "votes_count": 41, "ships_count": 0, "projects": [], "coding_time_seconds": 167163, "coding_time_seconds_today": 0, "balance": "You need to have a pocket watcher badge to view this.", "badges": [{"name": "Maiden Voyage", "text": "you shipped your first project! the journey begins...", "icon": "\ud83d\udea2"}], "created_at": "2025-07-18T11:37:53.376-04:00", "updated_at": "2025-09-15T08:42:37.492-04:00", "avatar": "https://secure.gravatar.com/avatar/a18faf0e9419ddd84f6ebde13b9b7415.jpg?s=512&d=https%3A%2F%2Fa.slack-edge.com%2Fdf10d%2Fimg%2Favatars%2Fava_0007-512.png", "custom_css": null}, {"id": 15973, "slack_id": "U09757NT4CQ", "display_name": "Alec", "bio": null, "projects_count": 1, "devlogs_count": 12, "votes_count": 23, "ships_count": 1, "projects": [{"id": 13573, "title": "Custom Linux distro using a NixOS flake", "devlogs_count": 7, "created_at": "2025-09-19T19:44:21.945-04:00"}], "coding_time_seconds": 179407, "coding_time_seconds_today": 0, "balance": "You need to have a pocket watcher badge to view this.", "badges": [{"name": "Maiden Voyage", "text": "you shipped your first project! the journey begins...", "icon": "\ud83d\udea2"}], "created_at": "2025-07-18T11:38:57.153-04:00", "updated_at": "2025-09-21T03:22:04.696-04:00", "avatar": "https://avatars.slack-edge.com/2025-09-18/9571234087648_f010624084afd34ddaa3_original.jpg", "custom_css": null}, {"id": 15974, "slack_id": "U095RD2NX8F", "display_name": "emb3rcia", "bio": null, "projects_count": 2, "devlogs_count": 2, "votes_count": 1, "ships_count": 1, "projects": [{"id": 11763, "title": "tinyspark", "devlogs_count": 0, "created_at": "2025-08-19T10:22:36.978-04:00"}, {"id": 10068, "title": "portfolio", "devlogs_count": 2, "created_at": "2025-08-03T20:14:16.221-04:00"}], "coding_time_seconds": 46621, "coding_time_seconds_today": 0, "balance": "You need to have a pocket watcher badge to view this.", "badges": [{"name": "Maiden Voyage", "text": "you shipped your first project! the journey begins...", "icon": "\ud83d\udea2"}], "created_at": "2025-07-18T12:35:27.942-04:00", "updated_at": "2025-09-10T22:59:02.149-04:00", "avatar": "https://secure.gravatar.com/avatar/a9c86fa574dd7151a96f1a6ae684503c.jpg?s=512&d=https%3A%2F%2Fa.slack-edge.com%2Fdf10d%2Fimg%2Favatars%2Fava_0013-512.png", "custom_css": null}, {"id": 15975, "slack_id": "U07RSQNSMKJ", "display_name": "Padimo", "bio": null, "projects_count": 2, "devlogs_count": 1, "votes_count": 10, "ships_count": 1, "projects": [{"id": 10581, "title": "Zip", "devlogs_count": 1, "created_at": "2025-08-08T11:41:36.507-04:00"}, {"id": 11016, "title": "Unplug Mac", "devlogs_count": 0, "created_at": "2025-08-12T11:53:22.818-04:00"}], "coding_time_seconds": 59879, "coding_time_seconds_today": 0, "balance": "You need to have a pocket watcher badge to view this.", "badges": [{"name": "Maiden Voyage", "text": "you shipped your first project! the journey begins...", "icon": "\ud83d\udea2"}], "created_at": "2025-07-18T12:40:56.723-04:00", "updated_at": "2025-09-10T22:59:02.178-04:00", "avatar": "https://avatars.slack-edge.com/2025-08-27/9419388143842_abdf35a7088b1b0349b5_original.png", "custom_css": null}, {"id": 15976, "slack_id": "U096WCQ486M", "display_name": "SHUBHAM NAYAK", "bio": null, "projects_count": 0, "devlogs_count": 0, "votes_count": 0, "ships_count": 0, "projects": [], "coding_time_seconds": 0, "coding_time_seconds_today": 0, "balance": "You need to have a pocket watcher badge to view this.", "badges": [], "created_at": "2025-07-18T12:53:09.238-04:00", "updated_at": "2025-07-18T21:24:55.186-04:00", "avatar": "https://avatars.slack-edge.com/2025-07-18/9234447922641_a8eea5efc68454612afa_original.png", "custom_css": null}, {"id": 15977, "slack_id": "U096BLKST51", "display_name": "saddex", "bio": null, "projects_count": 0, "devlogs_count": 0, "votes_count": 0, "ships_count": 0, "projects": [], "coding_time_seconds": 1725, "coding_time_seconds_today": 0, "balance": "You need to have a pocket watcher badge to view this.", "badges": [], "created_at": "2025-07-18T13:00:27.547-04:00", "updated_at": "2025-07-18T21:24:55.292-04:00", "avatar": "https://secure.gravatar.com/avatar/206ae9cadc93c50869e1bca6ea9bcba3.jpg?s=512&d=https%3A%2F%2Fa.slack-edge.com%2Fdf10d%2Fimg%2Favatars%2Fava_0002-512.png", "custom_css": null}, {"id": 15978, "slack_id": "U096BMB90QK", "display_name": "Jack Bird", "bio": null, "projects_count": 0, "devlogs_count": 0, "votes_count": 0, "ships_count": 0, "projects": [], "coding_time_seconds": 0, "coding_time_seconds_today": 0, "balance": "You need to have a pocket watcher badge to view this.", "badges": [], "created_at": "2025-07-18T13:03:17.738-04:00", "updated_at": "2025-07-18T21:24:55.397-04:00", "avatar": "https://secure.gravatar.com/avatar/57b1e178393cc12587a34ee2d880a620.jpg?s=512&d=https%3A%2F%2Fa.slack-edge.com%2Fdf10d%2Fimg%2Favatars%2Fava_0007-512.png", "custom_css": null}, {"id": 15979, "slack_id": "U096RH3CA65", "display_name": "Sarthak Jain", "bio": null, "projects_count": 0, "devlogs_count": 0, "votes_count": 0, "ships_count": 0, "projects": [], "coding_time_seconds": 142107, "coding_time_seconds_today": 0, "balance": "You need to have a pocket watcher badge to view this.", "badges": [], "created_at": "2025-07-18T13:04:50.398-04:00", "updated_at": "2025-08-14T12:44:59.110-04:00", "avatar": "https://avatars.slack-edge.com/2025-07-18/9234846551921_22f8418618a1cf276a0a_original.jpg", "custom_css": null}, {"id": 15980, "slack_id": "U096WJE68KT", "display_name": "Piyush Rajput", "bio": null, "projects_count": 0, "devlogs_count": 0, "votes_count": 0, "ships_count": 0, "projects": [], "coding_time_seconds": 0, "coding_time_seconds_today": 0, "balance": "You need to have a pocket watcher badge to view this.", "badges": [], "created_at": "2025-07-18T13:30:36.214-04:00", "updated_at": "2025-07-18T21:24:59.609-04:00", "avatar": "https://secure.gravatar.com/avatar/4a9649ece8c89847ad60800272b4d213.jpg?s=512&d=https%3A%2F%2Fa.slack-edge.com%2Fdf10d%2Fimg%2Favatars%2Fava_0021-512.png", "custom_css": null}, {"id": 15981, "slack_id": "U096DK7L7NJ", "display_name": "Vo Thanh Long", "bio": null, "projects_count": 0, "devlogs_count": 0, "votes_count": 0, "ships_count": 0, "projects": [], "coding_time_seconds": 0, "coding_time_seconds_today": 0, "balance": "You need to have a pocket watcher badge to view this.", "badges": [], "created_at": "2025-07-18T13:31:07.386-04:00", "updated_at": "2025-07-18T21:24:59.682-04:00", "avatar": "https://secure.gravatar.com/avatar/647b12adfded95703dcee6ab7fa8ea1d.jpg?s=512&d=https%3A%2F%2Fa.slack-edge.com%2Fdf10d%2Fimg%2Favatars%2Fava_0022-512.png", "custom_css": null}, {"id": 15982, "slack_id": "U091ZCEE0T0", "display_name": "Akarshan", "bio": null, "projects_count": 0, "devlogs_count": 0, "votes_count": 0, "ships_count": 0, "projects": [], "coding_time_seconds": 0, "coding_time_seconds_today": 0, "balance": "You need to have a pocket watcher badge to view this.", "badges": [], "created_at": "2025-07-18T13:35:09.620-04:00", "updated_at": "2025-07-18T21:24:59.773-04:00", "avatar": "https://secure.gravatar.com/avatar/e9fcb9688d0399ad9453460fc71617a3.jpg?s=512&d=https%3A%2F%2Fa.slack-edge.com%2Fdf10d%2Fimg%2Favatars%2Fava_0017-512.png", "custom_css": null}, {"id": 15983, "slack_id": "U077F2K0M45", "display_name": "Shoaib Memon", "bio": null, "projects_count": 0, "devlogs_count": 0, "votes_count": 0, "ships_count": 0, "projects": [], "coding_time_seconds": 0, "coding_time_seconds_today": 0, "balance": "You need to have a pocket watcher badge to view this.", "badges": [], "created_at": "2025-07-18T13:39:56.042-04:00", "updated_at": "2025-07-18T21:24:59.848-04:00", "avatar": "https://avatars.slack-edge.com/2025-07-18/9234687814785_6f76fd0c4669fb18fb8d_original.jpg", "custom_css": null}, {"id": 15984, "slack_id": "U096J9JHGH2", "display_name": "pawan", "bio": null, "projects_count": 0, "devlogs_count": 0, "votes_count": 0, "ships_count": 0, "projects": [], "coding_time_seconds": 0, "coding_time_seconds_today": 0, "balance": "You need to have a pocket watcher badge to view this.", "badges": [], "created_at": "2025-07-18T13:44:20.478-04:00", "updated_at": "2025-07-18T21:24:59.920-04:00", "avatar": "https://secure.gravatar.com/avatar/7e8b41ffff54fc72bf2839375c21f9c7.jpg?s=512&d=https%3A%2F%2Fa.slack-edge.com%2Fdf10d%2Fimg%2Favatars%2Fava_0013-512.png", "custom_css": null}, {"id": 15985, "slack_id": "U096JBKGZMJ", "display_name": "Ahmad", "bio": null, "projects_count": 0, "devlogs_count": 0, "votes_count": 0, "ships_count": 0, "projects": [], "coding_time_seconds": 0, "coding_time_seconds_today": 0, "balance": "You need to have a pocket watcher badge to view this.", "badges": [], "created_at": "2025-07-18T13:57:06.247-04:00", "updated_at": "2025-07-18T21:25:00.018-04:00", "avatar": "https://secure.gravatar.com/avatar/1ab0eb290d633d59cc4f77bae55fab4a.jpg?s=512&d=https%3A%2F%2Fa.slack-edge.com%2Fdf10d%2Fimg%2Favatars%2Fava_0013-512.png", "custom_css": null}], "pagination": {"page": 795, "pages": 1192, "count": 23828, "items": 20}}